pelican/plugins/pelican_feed_stylesheet/__init__.py
pelican/plugins/pelican_feed_stylesheet/feeds.py
pelican/plugins/pelican_feed_stylesheet/pelican_feed_stylesheet.py
pelican/plugins/pelican_feed_stylesheet/test_feeds.py
pelican/plugins/pelican_feed_stylesheet/test_pelican_feed_stylesheet.py
pelican_feed_stylesheet-0.0.1.dist-info/WHEEL
pelican_feed_stylesheet-0.0.1.dist-info/METADATA
pelican_feed_stylesheet-0.0.1.dist-info/RECORD
