Metadata-Version: 2.1
Name: pelican-feed-stylesheet
Version: 0.0.1
Summary: Enables use of xml stylesheets for human-readable feed generation.
Home-page: https://github.com/andrlik/pelican-feed-stylesheet
License: BSD-3-Clause
Keywords: pelican,plugin
Author: Daniel Andrlik
Author-email: daniel@andrlik.org
Requires-Python: >=3.6.2,<4.0
Classifier: Development Status :: 2 - Pre-Alpha
Classifier: Environment :: Console
Classifier: Framework :: Pelican
Classifier: Framework :: Pelican :: Plugins
Classifier: Intended Audience :: End Users/Desktop
Classifier: License :: OSI Approved :: BSD License
Classifier: Operating System :: OS Independent
Classifier: Programming Language :: Python :: 3
Classifier: Programming Language :: Python :: 3.10
Classifier: Programming Language :: Python :: 3.7
Classifier: Programming Language :: Python :: 3.8
Classifier: Programming Language :: Python :: 3.9
Classifier: Topic :: Internet :: WWW/HTTP
Classifier: Topic :: Software Development :: Libraries :: Python Modules
Provides-Extra: markdown
Requires-Dist: markdown (>=3.2); extra == "markdown"
Requires-Dist: pelican (>=4.5)
Project-URL: Documentation, https://docs.getpelican.com
Project-URL: Funding, https://donate.getpelican.com/
Project-URL: Issue Tracker, https://github.com/andrlik/pelican-feed-stylesheet/issues
Project-URL: Repository, https://github.com/andrlik/pelican-feed-stylesheet
